{"id": "kzh5APxAAHA", "title": "Behr - Polka WR: Polka W. R.", "formats": [{"asr": 48000, "filesize": 1629212, "format_id": "249", "format_note": "tiny", "fps": null, "height": null, "quality": 0, "tbr": 54.302, "url": "https://rr3---sn-0opoxu-ihv6.googlevideo.com/videoplayback?expire=1670725405&ei=veqUY5-cD430kgbHo7z4Cw&ip=189.173.225.87&id=o-AB55eTwYoeGbOIUUks_yc4l81ozMvy0OP8sXmPgo5cV8&itag=249&source=youtube&requiressl=yes&mh=Zc&mm=31%2C29&mn=sn-0opoxu-ihv6%2Csn-q4fl6nsd&ms=au%2Crdu&mv=m&mvi=3&pcm2cms=yes&pl=24&gcr=mx&initcwndbps=770000&vprv=1&mime=audio%2Fwebm&ns=WHou0Ed7y_5QtnuQlAdJa88J&gir=yes&clen=1629212&dur=240.021&lmt=1613126074244023&mt=1670703434&fvip=4&keepalive=yes&fexp=24001373%2C24007246&c=WEB&txp=1211222&n=wIGytpTVEhazb-6lT&sparams=expire%2Cei%2Cip%2Cid%2Citag%2Csource%2Crequiressl%2Cgcr%2Cvprv%2Cmime%2Cns%2Cgir%2Cclen%2Cdur%2Clmt&lsparams=mh%2Cmm%2Cmn%2Cms%2Cmv%2Cmvi%2Cpcm2cms%2Cpl%2Cinitcwndbps&lsig=AG3C_xAwRgIhAL1pZU4v74Fflb0VoyHXj8u0wu-9-4rL7dY_XDYO0Bo-AiEAn1-8gpa60UAVnxVxSh2Nkvx3G-HZbtcwH46j4qnmqWw%3D&sig=AOq0QJ8wRQIgCkaSqcoMEDs6IM0mE_Hihdb3KL9-R8jPHNl4GAUXATQCIQDoD6BfAktR1rjnKUPUczyvkc0kuTybwP7uduAllzzQ7Q==", "width": null, "ext": "webm", "vcodec": "none", "acodec": "opus", "abr": 54.302, "downloader_options": {"http_chunk_size": 10485760}, "container": "webm_dash", "format": "249 - audio only (tiny)", "protocol": "https", "http_headers": {"User-Agent": "Mozilla/5.0 (Windows NT 10.0; Win64; x64) AppleWebKit/537.36 (KHTML, like Gecko) Chrome/70.0.3529.3 Safari/537.36", "Accept-Charset": "ISO-8859-1,utf-8;q=0.7,*;q=0.7", "Accept": "text/html,application/xhtml+xml,application/xml;q=0.9,*/*;q=0.8", "Accept-Encoding": "gzip, deflate", "Accept-Language": "en-us,en;q=0.5"}}, {"asr": 48000, "filesize": 2155355, "format_id": "250", "format_note": "tiny", "fps": null, "height": null, "quality": 0, "tbr": 71.838, "url": "https://rr3---sn-0opoxu-ihv6.googlevideo.com/videoplayback?expire=1670725405&ei=veqUY5-cD430kgbHo7z4Cw&ip=189.173.225.87&id=o-AB55eTwYoeGbOIUUks_yc4l81ozMvy0OP8sXmPgo5cV8&itag=250&source=youtube&requiressl=yes&mh=Zc&mm=31%2C29&mn=sn-0opoxu-ihv6%2Csn-q4fl6nsd&ms=au%2Crdu&mv=m&mvi=3&pcm2cms=yes&pl=24&gcr=mx&initcwndbps=770000&vprv=1&mime=audio%2Fwebm&ns=WHou0Ed7y_5QtnuQlAdJa88J&gir=yes&clen=2155355&dur=240.021&lmt=1613126059839701&mt=1670703434&fvip=4&keepalive=yes&fexp=24001373%2C24007246&c=WEB&txp=1211222&n=wIGytpTVEhazb-6lT&sparams=expire%2Cei%2Cip%2Cid%2Citag%2Csource%2Crequiressl%2Cgcr%2Cvprv%2Cmime%2Cns%2Cgir%2Cclen%2Cdur%2Clmt&lsparams=mh%2Cmm%2Cmn%2Cms%2Cmv%2Cmvi%2Cpcm2cms%2Cpl%2Cinitcwndbps&lsig=AG3C_xAwRQIhAJiku5x_geyikR0CrmSlMm8VfexZR52roQK9cIG9iLM2AiBOd8IWSxcD1C11Y0YeZOIpYFY9hz_bWams2u0vlaRIlA%3D%3D&sig=AOq0QJ8wRQIgZb7elzJS3_kibPio06Xm0e7z1RgoJIltp331AFUFhqECIQCs7WnqQR80UKGNEDB1FsgPsA2kQVo7I8isi10PVabilA==", "width": null, "ext": "webm", "vcodec": "none", "acodec": "opus", "abr": 71.838, "downloader_options": {"http_chunk_size": 10485760}, "container": "webm_dash", "format": "250 - audio only (tiny)", "protocol": "https", "http_headers": {"User-Agent": "Mozilla/5.0 (Windows NT 10.0; Win64; x64) AppleWebKit/537.36 (KHTML, like Gecko) Chrome/70.0.3529.3 Safari/537.36", "Accept-Charset": "ISO-8859-1,utf-8;q=0.7,*;q=0.7", "Accept": "text/html,application/xhtml+xml,application/xml;q=0.9,*/*;q=0.8", "Accept-Encoding": "gzip, deflate", "Accept-Language": "en-us,en;q=0.5"}}, {"asr": 44100, "filesize": 3886051, "format_id": "140", "format_note": "tiny", "fps": null, "height": null, "quality": 0, "tbr": 129.535, "url": "https://rr3---sn-0opoxu-ihv6.googlevideo.com/videoplayback?expire=1670725405&ei=veqUY5-cD430kgbHo7z4Cw&ip=189.173.225.87&id=o-AB55eTwYoeGbOIUUks_yc4l81ozMvy0OP8sXmPgo5cV8&itag=140&source=youtube&requiressl=yes&mh=Zc&mm=31%2C29&mn=sn-0opoxu-ihv6%2Csn-q4fl6nsd&ms=au%2Crdu&mv=m&mvi=3&pcm2cms=yes&pl=24&gcr=mx&initcwndbps=770000&vprv=1&mime=audio%2Fmp4&ns=WHou0Ed7y_5QtnuQlAdJa88J&gir=yes&clen=3886051&dur=239.999&lmt=1612952041637678&mt=1670703434&fvip=4&keepalive=yes&fexp=24001373%2C24007246&c=WEB&txp=1211222&n=wIGytpTVEhazb-6lT&sparams=expire%2Cei%2Cip%2Cid%2Citag%2Csource%2Crequiressl%2Cgcr%2Cvprv%2Cmime%2Cns%2Cgir%2Cclen%2Cdur%2Clmt&lsparams=mh%2Cmm%2Cmn%2Cms%2Cmv%2Cmvi%2Cpcm2cms%2Cpl%2Cinitcwndbps&lsig=AG3C_xAwRQIgEW-y-Uf2EVc5eQGgFNLVdTTdXnzbCxeQ9Vo4Gk1JvnoCIQDD5Dg4Q6FxeXEfkb2C9WGy0zzrQ1p9KuH0GYcWMasWGw%3D%3D&sig=AOq0QJ8wRgIhAI3WQgecCskuNO8jl3aHJI3figM9rq17wSmX7Gf5JUqYAiEA0r91B6j18SDn4o5cYy20PzeF49fTjHOipAtcyRBa8CY=", "width": null, "ext": "m4a", "vcodec": "none", "acodec": "mp4a.40.2", "abr": 129.535, "downloader_options": {"http_chunk_size": 10485760}, "container": "m4a_dash", "format": "140 - audio only (tiny)", "protocol": "https", "http_headers": {"User-Agent": "Mozilla/5.0 (Windows NT 10.0; Win64; x64) AppleWebKit/537.36 (KHTML, like Gecko) Chrome/70.0.3529.3 Safari/537.36", "Accept-Charset": "ISO-8859-1,utf-8;q=0.7,*;q=0.7", "Accept": "text/html,application/xhtml+xml,application/xml;q=0.9,*/*;q=0.8", "Accept-Encoding": "gzip, deflate", "Accept-Language": "en-us,en;q=0.5"}}, {"asr": 48000, "filesize": 4258517, "format_id": "251", "format_note": "tiny", "fps": null, "height": null, "quality": 0, "tbr": 141.938, "url": "https://rr3---sn-0opoxu-ihv6.googlevideo.com/videoplayback?expire=1670725405&ei=veqUY5-cD430kgbHo7z4Cw&ip=189.173.225.87&id=o-AB55eTwYoeGbOIUUks_yc4l81ozMvy0OP8sXmPgo5cV8&itag=251&source=youtube&requiressl=yes&mh=Zc&mm=31%2C29&mn=sn-0opoxu-ihv6%2Csn-q4fl6nsd&ms=au%2Crdu&mv=m&mvi=3&pcm2cms=yes&pl=24&gcr=mx&initcwndbps=770000&vprv=1&mime=audio%2Fwebm&ns=WHou0Ed7y_5QtnuQlAdJa88J&gir=yes&clen=4258517&dur=240.021&lmt=1613126059007003&mt=1670703434&fvip=4&keepalive=yes&fexp=24001373%2C24007246&c=WEB&txp=1211222&n=wIGytpTVEhazb-6lT&sparams=expire%2Cei%2Cip%2Cid%2Citag%2Csource%2Crequiressl%2Cgcr%2Cvprv%2Cmime%2Cns%2Cgir%2Cclen%2Cdur%2Clmt&lsparams=mh%2Cmm%2Cmn%2Cms%2Cmv%2Cmvi%2Cpcm2cms%2Cpl%2Cinitcwndbps&lsig=AG3C_xAwRQIgLI5uFyb7YoRgLn_0DSBAlXMYoTNbiRWXy4ayACMnldwCIQCPfhYI57OEpVZeDZvnVb6ogtK60RZcSRNx0_JLMNZg3Q%3D%3D&sig=AOq0QJ8wRAIgQmoHyb400DUJHVdkJqLDI1JV-ssBUdtaypSS_o1Z1HwCIBBvQSK4dnqDBW9hC146dsJrshnuBhWn1Hfb3v4Hw4hy", "width": null, "ext": "webm", "vcodec": "none", "acodec": "opus", "abr": 141.938, "downloader_options": {"http_chunk_size": 10485760}, "container": "webm_dash", "format": "251 - audio only (tiny)", "protocol": "https", "http_headers": {"User-Agent": "Mozilla/5.0 (Windows NT 10.0; Win64; x64) AppleWebKit/537.36 (KHTML, like Gecko) Chrome/70.0.3529.3 Safari/537.36", "Accept-Charset": "ISO-8859-1,utf-8;q=0.7,*;q=0.7", "Accept": "text/html,application/xhtml+xml,application/xml;q=0.9,*/*;q=0.8", "Accept-Encoding": "gzip, deflate", "Accept-Language": "en-us,en;q=0.5"}}, {"asr": null, "filesize": 642717, "format_id": "278", "format_note": "144p", "fps": 25, "height": 144, "quality": 0, "tbr": 21.423, "url": "https://rr3---sn-0opoxu-ihv6.googlevideo.com/videoplayback?expire=1670725405&ei=veqUY5-cD430kgbHo7z4Cw&ip=189.173.225.87&id=o-AB55eTwYoeGbOIUUks_yc4l81ozMvy0OP8sXmPgo5cV8&itag=278&aitags=133%2C134%2C135%2C136%2C137%2C160%2C242%2C243%2C244%2C247%2C248%2C278&source=youtube&requiressl=yes&mh=Zc&mm=31%2C29&mn=sn-0opoxu-ihv6%2Csn-q4fl6nsd&ms=au%2Crdu&mv=m&mvi=3&pcm2cms=yes&pl=24&gcr=mx&initcwndbps=770000&vprv=1&mime=video%2Fwebm&ns=WHou0Ed7y_5QtnuQlAdJa88J&gir=yes&clen=642717&dur=240.000&lmt=1613126182812464&mt=1670703434&fvip=4&keepalive=yes&fexp=24001373%2C24007246&c=WEB&txp=1211222&n=wIGytpTVEhazb-6lT&sparams=expire%2Cei%2Cip%2Cid%2Caitags%2Csource%2Crequiressl%2Cgcr%2Cvprv%2Cmime%2Cns%2Cgir%2Cclen%2Cdur%2Clmt&lsparams=mh%2Cmm%2Cmn%2Cms%2Cmv%2Cmvi%2Cpcm2cms%2Cpl%2Cinitcwndbps&lsig=AG3C_xAwRQIhAMa4zpInWyunWEoZLtcX-1aD3617-jBFTs2KXiwOmYzVAiAvLhTAZAS9ewW42Sk7yeRXXL5c15UnjPyWef5fdnl_aw%3D%3D&sig=AOq0QJ8wRAIgHIHiv-g6eAWSNhUkOzfZM2XXEvcA8X5soQDQffkROqACIHLPw4QbV10jUlVUXjA2-2kr8Vn_qKEmD1xzYgT_XWrR", "width": 144, "ext": "webm", "vcodec": "vp9", "acodec": "none", "vbr": 21.423, "downloader_options": {"http_chunk_size": 10485760}, "container": "webm_dash", "format": "278 - 144x144 (144p)", "protocol": "https", "http_headers": {"User-Agent": "Mozilla/5.0 (Windows NT 10.0; Win64; x64) AppleWebKit/537.36 (KHTML, like Gecko) Chrome/70.0.3529.3 Safari/537.36", "Accept-Charset": "ISO-8859-1,utf-8;q=0.7,*;q=0.7", "Accept": "text/html,application/xhtml+xml,application/xml;q=0.9,*/*;q=0.8", "Accept-Encoding": "gzip, deflate", "Accept-Language": "en-us,en;q=0.5"}}, {"asr": null, "filesize": 807352, "format_id": "160", "format_note": "144p", "fps": 25, "height": 144, "quality": 0, "tbr": 26.911, "url": "https://rr3---sn-0opoxu-ihv6.googlevideo.com/videoplayback?expire=1670725405&ei=veqUY5-cD430kgbHo7z4Cw&ip=189.173.225.87&id=o-AB55eTwYoeGbOIUUks_yc4l81ozMvy0OP8sXmPgo5cV8&itag=160&aitags=133%2C134%2C135%2C136%2C137%2C160%2C242%2C243%2C244%2C247%2C248%2C278&source=youtube&requiressl=yes&mh=Zc&mm=31%2C29&mn=sn-0opoxu-ihv6%2Csn-q4fl6nsd&ms=au%2Crdu&mv=m&mvi=3&pcm2cms=yes&pl=24&gcr=mx&initcwndbps=770000&vprv=1&mime=video%2Fmp4&ns=WHou0Ed7y_5QtnuQlAdJa88J&gir=yes&clen=807352&dur=240.000&lmt=1612952044941918&mt=1670703434&fvip=4&keepalive=yes&fexp=24001373%2C24007246&c=WEB&txp=1211222&n=wIGytpTVEhazb-6lT&sparams=expire%2Cei%2Cip%2Cid%2Caitags%2Csource%2Crequiressl%2Cgcr%2Cvprv%2Cmime%2Cns%2Cgir%2Cclen%2Cdur%2Clmt&lsparams=mh%2Cmm%2Cmn%2Cms%2Cmv%2Cmvi%2Cpcm2cms%2Cpl%2Cinitcwndbps&lsig=AG3C_xAwRQIhALijqxcuk-xBZ7awCnhLBNOpYWUZnhqPHwZsnrjWJ3oWAiAhipXtEEYoZVyDbeqwT0A6Gt9-mxvI9lpNFlPfUZgpRg%3D%3D&sig=AOq0QJ8wRgIhAOvZACNzHlv9zBRjQqcSjXOjRoX-Vz00-vdE6c8UwFDGAiEAuLGMD7T7aN_M7w6WRahGc4donp75LdrjO-fAy5mKiqs=", "width": 144, "ext": "mp4", "vcodec": "avc1.4d400b", "acodec": "none", "vbr": 26.911, "downloader_options": {"http_chunk_size": 10485760}, "container": "mp4_dash", "format": "160 - 144x144 (144p)", "protocol": "https", "http_headers": {"User-Agent": "Mozilla/5.0 (Windows NT 10.0; Win64; x64) AppleWebKit/537.36 (KHTML, like Gecko) Chrome/70.0.3529.3 Safari/537.36", "Accept-Charset": "ISO-8859-1,utf-8;q=0.7,*;q=0.7", "Accept": "text/html,application/xhtml+xml,application/xml;q=0.9,*/*;q=0.8", "Accept-Encoding": "gzip, deflate", "Accept-Language": "en-us,en;q=0.5"}}, {"asr": null, "filesize": 1301435, "format_id": "242", "format_note": "240p", "fps": 25, "height": 240, "quality": 1, "tbr": 43.381, "url": "https://rr3---sn-0opoxu-ihv6.googlevideo.com/videoplayback?expire=1670725405&ei=veqUY5-cD430kgbHo7z4Cw&ip=189.173.225.87&id=o-AB55eTwYoeGbOIUUks_yc4l81ozMvy0OP8sXmPgo5cV8&itag=242&aitags=133%2C134%2C135%2C136%2C137%2C160%2C242%2C243%2C244%2C247%2C248%2C278&source=youtube&requiressl=yes&mh=Zc&mm=31%2C29&mn=sn-0opoxu-ihv6%2Csn-q4fl6nsd&ms=au%2Crdu&mv=m&mvi=3&pcm2cms=yes&pl=24&gcr=mx&initcwndbps=770000&vprv=1&mime=video%2Fwebm&ns=WHou0Ed7y_5QtnuQlAdJa88J&gir=yes&clen=1301435&dur=240.000&lmt=1613126182730032&mt=1670703434&fvip=4&keepalive=yes&fexp=24001373%2C24007246&c=WEB&txp=1211222&n=wIGytpTVEhazb-6lT&sparams=expire%2Cei%2Cip%2Cid%2Caitags%2Csource%2Crequiressl%2Cgcr%2Cvprv%2Cmime%2Cns%2Cgir%2Cclen%2Cdur%2Clmt&lsparams=mh%2Cmm%2Cmn%2Cms%2Cmv%2Cmvi%2Cpcm2cms%2Cpl%2Cinitcwndbps&lsig=AG3C_xAwRAIgO0FGPJqGLSrC_jdYNb1vDvH22kHN5bUidjPvwIx3nIMCIDTzpkOe_tt9bxaisDyiIjWgtOiwJAx3CDkaNQqvt0o9&sig=AOq0QJ8wRQIgdYr6ER6ilpbo2-tcgY4AiWTaiwcfbtSLBq-_b60q6ncCIQDX1fDbzRMUT2CXzMolwYZsWifoDdhl3gREYKPuOG8s0g==", "width": 240, "ext": "webm", "vcodec": "vp9", "acodec": "none", "vbr": 43.381, "downloader_options": {"http_chunk_size": 10485760}, "container": "webm_dash", "format": "242 - 240x240 (240p)", "protocol": "https", "http_headers": {"User-Agent": "Mozilla/5.0 (Windows NT 10.0; Win64; x64) AppleWebKit/537.36 (KHTML, like Gecko) Chrome/70.0.3529.3 Safari/537.36", "Accept-Charset": "ISO-8859-1,utf-8;q=0.7,*;q=0.7", "Accept": "text/html,application/xhtml+xml,application/xml;q=0.9,*/*;q=0.8", "Accept-Encoding": "gzip, deflate", "Accept-Language": "en-us,en;q=0.5"}}, {"asr": null, "filesize": 1756022, "format_id": "133", "format_note": "240p", "fps": 25, "height": 240, "quality": 1, "tbr": 58.534, "url": "https://rr3---sn-0opoxu-ihv6.googlevideo.com/videoplayback?expire=1670725405&ei=veqUY5-cD430kgbHo7z4Cw&ip=189.173.225.87&id=o-AB55eTwYoeGbOIUUks_yc4l81ozMvy0OP8sXmPgo5cV8&itag=133&aitags=133%2C134%2C135%2C136%2C137%2C160%2C242%2C243%2C244%2C247%2C248%2C278&source=youtube&requiressl=yes&mh=Zc&mm=31%2C29&mn=sn-0opoxu-ihv6%2Csn-q4fl6nsd&ms=au%2Crdu&mv=m&mvi=3&pcm2cms=yes&pl=24&gcr=mx&initcwndbps=770000&vprv=1&mime=video%2Fmp4&ns=WHou0Ed7y_5QtnuQlAdJa88J&gir=yes&clen=1756022&dur=240.000&lmt=1612952105456790&mt=1670703434&fvip=4&keepalive=yes&fexp=24001373%2C24007246&c=WEB&txp=1211222&n=wIGytpTVEhazb-6lT&sparams=expire%2Cei%2Cip%2Cid%2Caitags%2Csource%2Crequiressl%2Cgcr%2Cvprv%2Cmime%2Cns%2Cgir%2Cclen%2Cdur%2Clmt&lsparams=mh%2Cmm%2Cmn%2Cms%2Cmv%2Cmvi%2Cpcm2cms%2Cpl%2Cinitcwndbps&lsig=AG3C_xAwRgIhAOW8pqSi8Oo8BQHIysRWVXAGPy2El5-vugc2yl9H1TFGAiEApUesEEgwCwZvDgfPVLNCDoV-Po-r4HBp2lE3gZdxnYw%3D&sig=AOq0QJ8wRQIgL-duzZ3gBoaCUB64JxpXeElB3uh-vV5qiC51giAjrhwCIQCymeu8WHsFtMSa-Ayp8YITDBEwZMucSZ3bUKv0zu4R-w==", "width": 240, "ext": "mp4", "vcodec": "avc1.4d400c", "acodec": "none", "vbr": 58.534, "downloader_options": {"http_chunk_size": 10485760}, "container": "mp4_dash", "format": "133 - 240x240 (240p)", "protocol": "https", "http_headers": {"User-Agent": "Mozilla/5.0 (Windows NT 10.0; Win64; x64) AppleWebKit/537.36 (KHTML, like Gecko) Chrome/70.0.3529.3 Safari/537.36", "Accept-Charset": "ISO-8859-1,utf-8;q=0.7,*;q=0.7", "Accept": "text/html,application/xhtml+xml,application/xml;q=0.9,*/*;q=0.8", "Accept-Encoding": "gzip, deflate", "Accept-Language": "en-us,en;q=0.5"}}, {"asr": null, "filesize": 1116798, "format_id": "134", "format_note": "360p", "fps": 25, "height": 360, "quality": 2, "tbr": 37.226, "url": "https://rr3---sn-0opoxu-ihv6.googlevideo.com/videoplayback?expire=1670725405&ei=veqUY5-cD430kgbHo7z4Cw&ip=189.173.225.87&id=o-AB55eTwYoeGbOIUUks_yc4l81ozMvy0OP8sXmPgo5cV8&itag=134&aitags=133%2C134%2C135%2C136%2C137%2C160%2C242%2C243%2C244%2C247%2C248%2C278&source=youtube&requiressl=yes&mh=Zc&mm=31%2C29&mn=sn-0opoxu-ihv6%2Csn-q4fl6nsd&ms=au%2Crdu&mv=m&mvi=3&pcm2cms=yes&pl=24&gcr=mx&initcwndbps=770000&vprv=1&mime=video%2Fmp4&ns=WHou0Ed7y_5QtnuQlAdJa88J&gir=yes&clen=1116798&dur=240.000&lmt=1612952046584766&mt=1670703434&fvip=4&keepalive=yes&fexp=24001373%2C24007246&c=WEB&txp=1211222&n=wIGytpTVEhazb-6lT&sparams=expire%2Cei%2Cip%2Cid%2Caitags%2Csource%2Crequiressl%2Cgcr%2Cvprv%2Cmime%2Cns%2Cgir%2Cclen%2Cdur%2Clmt&lsparams=mh%2Cmm%2Cmn%2Cms%2Cmv%2Cmvi%2Cpcm2cms%2Cpl%2Cinitcwndbps&lsig=AG3C_xAwRAIgWelIKKMS2AUECgoVFBV2wTpQ_UHO5WbHxgACRzqHiHcCIFZ8pxDRHMLKIUcX-qsheLUOpBNsVVdlaOpemBzwRPdR&sig=AOq0QJ8wRAIgMMRnTWHonLwlslFxbz7ewDwJSoD8tUnQZs6KOVifRIQCIF15njLdrcxpiIE1HWRQOE1flTYb7tDc9qwzmHhqrLFx", "width": 360, "ext": "mp4", "vcodec": "avc1.4d4015", "acodec": "none", "vbr": 37.226, "downloader_options": {"http_chunk_size": 10485760}, "container": "mp4_dash", "format": "134 - 360x360 (360p)", "protocol": "https", "http_headers": {"User-Agent": "Mozilla/5.0 (Windows NT 10.0; Win64; x64) AppleWebKit/537.36 (KHTML, like Gecko) Chrome/70.0.3529.3 Safari/537.36", "Accept-Charset": "ISO-8859-1,utf-8;q=0.7,*;q=0.7", "Accept": "text/html,application/xhtml+xml,application/xml;q=0.9,*/*;q=0.8", "Accept-Encoding": "gzip, deflate", "Accept-Language": "en-us,en;q=0.5"}}, {"asr": null, "filesize": 2337840, "format_id": "243", "format_note": "360p", "fps": 25, "height": 360, "quality": 2, "tbr": 77.928, "url": "https://rr3---sn-0opoxu-ihv6.googlevideo.com/videoplayback?expire=1670725405&ei=veqUY5-cD430kgbHo7z4Cw&ip=189.173.225.87&id=o-AB55eTwYoeGbOIUUks_yc4l81ozMvy0OP8sXmPgo5cV8&itag=243&aitags=133%2C134%2C135%2C136%2C137%2C160%2C242%2C243%2C244%2C247%2C248%2C278&source=youtube&requiressl=yes&mh=Zc&mm=31%2C29&mn=sn-0opoxu-ihv6%2Csn-q4fl6nsd&ms=au%2Crdu&mv=m&mvi=3&pcm2cms=yes&pl=24&gcr=mx&initcwndbps=770000&vprv=1&mime=video%2Fwebm&ns=WHou0Ed7y_5QtnuQlAdJa88J&gir=yes&clen=2337840&dur=240.000&lmt=1613126182721425&mt=1670703434&fvip=4&keepalive=yes&fexp=24001373%2C24007246&c=WEB&txp=1211222&n=wIGytpTVEhazb-6lT&sparams=expire%2Cei%2Cip%2Cid%2Caitags%2Csource%2Crequiressl%2Cgcr%2Cvprv%2Cmime%2Cns%2Cgir%2Cclen%2Cdur%2Clmt&lsparams=mh%2Cmm%2Cmn%2Cms%2Cmv%2Cmvi%2Cpcm2cms%2Cpl%2Cinitcwndbps&lsig=AG3C_xAwRAIgHlulEsy5um7gYe7QSgR-V7Id00V5ZRFiMJxsdE6HEi8CIBg3xMl5apJe2vk1NNGipMbWguKd1t6m4vAWTxxkQik7&sig=AOq0QJ8wRQIgLvJhgDY36K71Zi30vX2IpHseokv8TMf1YUEebDGuNO4CIQCGPQKbYFJR2vn_oMRmNYE8AShWrYANukbvemuWp16XyQ==", "width": 360, "ext": "webm", "vcodec": "vp9", "acodec": "none", "vbr": 77.928, "downloader_options": {"http_chunk_size": 10485760}, "container": "webm_dash", "format": "243 - 360x360 (360p)", "protocol": "https", "http_headers": {"User-Agent": "Mozilla/5.0 (Windows NT 10.0; Win64; x64) AppleWebKit/537.36 (KHTML, like Gecko) Chrome/70.0.3529.3 Safari/537.36", "Accept-Charset": "ISO-8859-1,utf-8;q=0.7,*;q=0.7", "Accept": "text/html,application/xhtml+xml,application/xml;q=0.9,*/*;q=0.8", "Accept-Encoding": "gzip, deflate", "Accept-Language": "en-us,en;q=0.5"}}, {"asr": null, "filesize": 2035019, "format_id": "135", "format_note": "480p", "fps": 25, "height": 480, "quality": 3, "tbr": 67.833, "url": "https://rr3---sn-0opoxu-ihv6.googlevideo.com/videoplayback?expire=1670725405&ei=veqUY5-cD430kgbHo7z4Cw&ip=189.173.225.87&id=o-AB55eTwYoeGbOIUUks_yc4l81ozMvy0OP8sXmPgo5cV8&itag=135&aitags=133%2C134%2C135%2C136%2C137%2C160%2C242%2C243%2C244%2C247%2C248%2C278&source=youtube&requiressl=yes&mh=Zc&mm=31%2C29&mn=sn-0opoxu-ihv6%2Csn-q4fl6nsd&ms=au%2Crdu&mv=m&mvi=3&pcm2cms=yes&pl=24&gcr=mx&initcwndbps=770000&vprv=1&mime=video%2Fmp4&ns=WHou0Ed7y_5QtnuQlAdJa88J&gir=yes&clen=2035019&dur=240.000&lmt=1612952048496286&mt=1670703434&fvip=4&keepalive=yes&fexp=24001373%2C24007246&c=WEB&txp=1211222&n=wIGytpTVEhazb-6lT&sparams=expire%2Cei%2Cip%2Cid%2Caitags%2Csource%2Crequiressl%2Cgcr%2Cvprv%2Cmime%2Cns%2Cgir%2Cclen%2Cdur%2Clmt&lsparams=mh%2Cmm%2Cmn%2Cms%2Cmv%2Cmvi%2Cpcm2cms%2Cpl%2Cinitcwndbps&lsig=AG3C_xAwRQIhAKrVY7y07oJGZjqrSGcxYcklSDCB266qRR4Zw2NkY-g-AiBBgwu6qIf2rToQts0Wq2OiuTIkETY1oQvelKynLXe1yw%3D%3D&sig=AOq0QJ8wRgIhAJ9wjhdhxIYL2xNqrKNnJzSjhBh2_-ilqJeMZK1CZ13_AiEA3yog5HAKKBbsptGucewftxIrgiKXQVFA12Rf5sfyijs=", "width": 480, "ext": "mp4", "vcodec": "avc1.4d401e", "acodec": "none", "vbr": 67.833, "downloader_options": {"http_chunk_size": 10485760}, "container": "mp4_dash", "format": "135 - 480x480 (480p)", "protocol": "https", "http_headers": {"User-Agent": "Mozilla/5.0 (Windows NT 10.0; Win64; x64) AppleWebKit/537.36 (KHTML, like Gecko) Chrome/70.0.3529.3 Safari/537.36", "Accept-Charset": "ISO-8859-1,utf-8;q=0.7,*;q=0.7", "Accept": "text/html,application/xhtml+xml,application/xml;q=0.9,*/*;q=0.8", "Accept-Encoding": "gzip, deflate", "Accept-Language": "en-us,en;q=0.5"}}, {"asr": null, "filesize": 3928870, "format_id": "244", "format_note": "480p", "fps": 25, "height": 480, "quality": 3, "tbr": 130.962, "url": "https://rr3---sn-0opoxu-ihv6.googlevideo.com/videoplayback?expire=1670725405&ei=veqUY5-cD430kgbHo7z4Cw&ip=189.173.225.87&id=o-AB55eTwYoeGbOIUUks_yc4l81ozMvy0OP8sXmPgo5cV8&itag=244&aitags=133%2C134%2C135%2C136%2C137%2C160%2C242%2C243%2C244%2C247%2C248%2C278&source=youtube&requiressl=yes&mh=Zc&mm=31%2C29&mn=sn-0opoxu-ihv6%2Csn-q4fl6nsd&ms=au%2Crdu&mv=m&mvi=3&pcm2cms=yes&pl=24&gcr=mx&initcwndbps=770000&vprv=1&mime=video%2Fwebm&ns=WHou0Ed7y_5QtnuQlAdJa88J&gir=yes&clen=3928870&dur=240.000&lmt=1613126182785388&mt=1670703434&fvip=4&keepalive=yes&fexp=24001373%2C24007246&c=WEB&txp=1211222&n=wIGytpTVEhazb-6lT&sparams=expire%2Cei%2Cip%2Cid%2Caitags%2Csource%2Crequiressl%2Cgcr%2Cvprv%2Cmime%2Cns%2Cgir%2Cclen%2Cdur%2Clmt&lsparams=mh%2Cmm%2Cmn%2Cms%2Cmv%2Cmvi%2Cpcm2cms%2Cpl%2Cinitcwndbps&lsig=AG3C_xAwRQIgCk1lL80jPnVmbSBYx1Wg2VShB0RciJ45kTMHagvUubICIQDETCk6rmRhoUVrhHpbadmhPOOH0fx5gWoelzRE_6CorA%3D%3D&sig=AOq0QJ8wRAIgEsPVgB5x8vLN9_XC3VnYC3fPDp8kD03E5mGgpUcK91ICICSPMGQWy-fGG4dg7fC-MnNdtGKPUGKZmQfWunOkP5ZA", "width": 480, "ext": "webm", "vcodec": "vp9", "acodec": "none", "vbr": 130.962, "downloader_options": {"http_chunk_size": 10485760}, "container": "webm_dash", "format": "244 - 480x480 (480p)", "protocol": "https", "http_headers": {"User-Agent": "Mozilla/5.0 (Windows NT 10.0; Win64; x64) AppleWebKit/537.36 (KHTML, like Gecko) Chrome/70.0.3529.3 Safari/537.36", "Accept-Charset": "ISO-8859-1,utf-8;q=0.7,*;q=0.7", "Accept": "text/html,application/xhtml+xml,application/xml;q=0.9,*/*;q=0.8", "Accept-Encoding": "gzip, deflate", "Accept-Language": "en-us,en;q=0.5"}}, {"asr": null, "filesize": 4101770, "format_id": "136", "format_note": "720p", "fps": 25, "height": 720, "quality": 4, "tbr": 136.725, "url": "https://rr3---sn-0opoxu-ihv6.googlevideo.com/videoplayback?expire=1670725405&ei=veqUY5-cD430kgbHo7z4Cw&ip=189.173.225.87&id=o-AB55eTwYoeGbOIUUks_yc4l81ozMvy0OP8sXmPgo5cV8&itag=136&aitags=133%2C134%2C135%2C136%2C137%2C160%2C242%2C243%2C244%2C247%2C248%2C278&source=youtube&requiressl=yes&mh=Zc&mm=31%2C29&mn=sn-0opoxu-ihv6%2Csn-q4fl6nsd&ms=au%2Crdu&mv=m&mvi=3&pcm2cms=yes&pl=24&gcr=mx&initcwndbps=770000&vprv=1&mime=video%2Fmp4&ns=WHou0Ed7y_5QtnuQlAdJa88J&gir=yes&clen=4101770&dur=240.000&lmt=1612952096224364&mt=1670703434&fvip=4&keepalive=yes&fexp=24001373%2C24007246&c=WEB&txp=1211222&n=wIGytpTVEhazb-6lT&sparams=expire%2Cei%2Cip%2Cid%2Caitags%2Csource%2Crequiressl%2Cgcr%2Cvprv%2Cmime%2Cns%2Cgir%2Cclen%2Cdur%2Clmt&lsparams=mh%2Cmm%2Cmn%2Cms%2Cmv%2Cmvi%2Cpcm2cms%2Cpl%2Cinitcwndbps&lsig=AG3C_xAwRQIhAJiCix4hqIczBJZ1jx49LZD9KbHy-duANModWF_6ZiU-AiB6psoEeer24J5h5_8Jqk8NVJFZNFLrhPLZUKwKAm48wA%3D%3D&sig=AOq0QJ8wRgIhALJ9fGaLXK6OLPiiIR5tidnYnpJq788kjhpwLoJ97eQpAiEA-64csagXL9i5LWUMPbmmBsYPqK9IJGloWznzEkYRQnc=", "width": 720, "ext": "mp4", "vcodec": "avc1.4d401f", "acodec": "none", "vbr": 136.725, "downloader_options": {"http_chunk_size": 10485760}, "container": "mp4_dash", "format": "136 - 720x720 (720p)", "protocol": "https", "http_headers": {"User-Agent": "Mozilla/5.0 (Windows NT 10.0; Win64; x64) AppleWebKit/537.36 (KHTML, like Gecko) Chrome/70.0.3529.3 Safari/537.36", "Accept-Charset": "ISO-8859-1,utf-8;q=0.7,*;q=0.7", "Accept": "text/html,application/xhtml+xml,application/xml;q=0.9,*/*;q=0.8", "Accept-Encoding": "gzip, deflate", "Accept-Language": "en-us,en;q=0.5"}}, {"asr": null, "filesize": 8339584, "format_id": "247", "format_note": "720p", "fps": 25, "height": 720, "quality": 4, "tbr": 277.986, "url": "https://rr3---sn-0opoxu-ihv6.googlevideo.com/videoplayback?expire=1670725405&ei=veqUY5-cD430kgbHo7z4Cw&ip=189.173.225.87&id=o-AB55eTwYoeGbOIUUks_yc4l81ozMvy0OP8sXmPgo5cV8&itag=247&aitags=133%2C134%2C135%2C136%2C137%2C160%2C242%2C243%2C244%2C247%2C248%2C278&source=youtube&requiressl=yes&mh=Zc&mm=31%2C29&mn=sn-0opoxu-ihv6%2Csn-q4fl6nsd&ms=au%2Crdu&mv=m&mvi=3&pcm2cms=yes&pl=24&gcr=mx&initcwndbps=770000&vprv=1&mime=video%2Fwebm&ns=WHou0Ed7y_5QtnuQlAdJa88J&gir=yes&clen=8339584&dur=240.000&lmt=1613126182740291&mt=1670703434&fvip=4&keepalive=yes&fexp=24001373%2C24007246&c=WEB&txp=1211222&n=wIGytpTVEhazb-6lT&sparams=expire%2Cei%2Cip%2Cid%2Caitags%2Csource%2Crequiressl%2Cgcr%2Cvprv%2Cmime%2Cns%2Cgir%2Cclen%2Cdur%2Clmt&lsparams=mh%2Cmm%2Cmn%2Cms%2Cmv%2Cmvi%2Cpcm2cms%2Cpl%2Cinitcwndbps&lsig=AG3C_xAwRgIhAPmvAnoMPv_-yZDoyZ6vZXrTE2_Q2cGPyNsAQgn52F9FAiEAn_qwCf5rldT5i94V1Gk0Ia4p_U8Z3blK36TYyRzkxxE%3D&sig=AOq0QJ8wRQIgEXc-IJ0wyC1L4_bvfGOxILuBGtBEavQQ-W6EFo0uH_8CIQC15l5e9bBgvgy_UwhAxp7nRmrEe6VN7AZsTjvTRilDNg==", "width": 720, "ext": "webm", "vcodec": "vp9", "acodec": "none", "vbr": 277.986, "downloader_options": {"http_chunk_size": 10485760}, "container": "webm_dash", "format": "247 - 720x720 (720p)", "protocol": "https", "http_headers": {"User-Agent": "Mozilla/5.0 (Windows NT 10.0; Win64; x64) AppleWebKit/537.36 (KHTML, like Gecko) Chrome/70.0.3529.3 Safari/537.36", "Accept-Charset": "ISO-8859-1,utf-8;q=0.7,*;q=0.7", "Accept": "text/html,application/xhtml+xml,application/xml;q=0.9,*/*;q=0.8", "Accept-Encoding": "gzip, deflate", "Accept-Language": "en-us,en;q=0.5"}}, {"asr": null, "filesize": 7629462, "format_id": "137", "format_note": "1080p", "fps": 25, "height": 1080, "quality": 5, "tbr": 254.315, "url": "https://rr3---sn-0opoxu-ihv6.googlevideo.com/videoplayback?expire=1670725405&ei=veqUY5-cD430kgbHo7z4Cw&ip=189.173.225.87&id=o-AB55eTwYoeGbOIUUks_yc4l81ozMvy0OP8sXmPgo5cV8&itag=137&aitags=133%2C134%2C135%2C136%2C137%2C160%2C242%2C243%2C244%2C247%2C248%2C278&source=youtube&requiressl=yes&mh=Zc&mm=31%2C29&mn=sn-0opoxu-ihv6%2Csn-q4fl6nsd&ms=au%2Crdu&mv=m&mvi=3&pcm2cms=yes&pl=24&gcr=mx&initcwndbps=770000&vprv=1&mime=video%2Fmp4&ns=WHou0Ed7y_5QtnuQlAdJa88J&gir=yes&clen=7629462&dur=240.000&lmt=1612952052581433&mt=1670703434&fvip=4&keepalive=yes&fexp=24001373%2C24007246&c=WEB&txp=1211222&n=wIGytpTVEhazb-6lT&sparams=expire%2Cei%2Cip%2Cid%2Caitags%2Csource%2Crequiressl%2Cgcr%2Cvprv%2Cmime%2Cns%2Cgir%2Cclen%2Cdur%2Clmt&lsparams=mh%2Cmm%2Cmn%2Cms%2Cmv%2Cmvi%2Cpcm2cms%2Cpl%2Cinitcwndbps&lsig=AG3C_xAwRQIhAJbUmRgISPAPfLGqAvb1lVMgsYdj3rk9e3baYIEQvamRAiAxuu9RenUHD7KMkX4b24if8MOJjKEuFB6ZEFMKpL6hCQ%3D%3D&sig=AOq0QJ8wRQIgFoK0o_1zwfKb2B63KAsMk7MN4sFzpHi0_EdJAutINI4CIQCadua0uFJMo6kUo4rUBiRes5VFlYWMiXgmImEL2OjE3w==", "width": 1080, "ext": "mp4", "vcodec": "avc1.640020", "acodec": "none", "vbr": 254.315, "downloader_options": {"http_chunk_size": 10485760}, "container": "mp4_dash", "format": "137 - 1080x1080 (1080p)", "protocol": "https", "http_headers": {"User-Agent": "Mozilla/5.0 (Windows NT 10.0; Win64; x64) AppleWebKit/537.36 (KHTML, like Gecko) Chrome/70.0.3529.3 Safari/537.36", "Accept-Charset": "ISO-8859-1,utf-8;q=0.7,*;q=0.7", "Accept": "text/html,application/xhtml+xml,application/xml;q=0.9,*/*;q=0.8", "Accept-Encoding": "gzip, deflate", "Accept-Language": "en-us,en;q=0.5"}}, {"asr": null, "filesize": 15950087, "format_id": "248", "format_note": "1080p", "fps": 25, "height": 1080, "quality": 5, "tbr": 531.669, "url": "https://rr3---sn-0opoxu-ihv6.googlevideo.com/videoplayback?expire=1670725405&ei=veqUY5-cD430kgbHo7z4Cw&ip=189.173.225.87&id=o-AB55eTwYoeGbOIUUks_yc4l81ozMvy0OP8sXmPgo5cV8&itag=248&aitags=133%2C134%2C135%2C136%2C137%2C160%2C242%2C243%2C244%2C247%2C248%2C278&source=youtube&requiressl=yes&mh=Zc&mm=31%2C29&mn=sn-0opoxu-ihv6%2Csn-q4fl6nsd&ms=au%2Crdu&mv=m&mvi=3&pcm2cms=yes&pl=24&gcr=mx&initcwndbps=770000&vprv=1&mime=video%2Fwebm&ns=WHou0Ed7y_5QtnuQlAdJa88J&gir=yes&clen=15950087&dur=240.000&lmt=1613126132062452&mt=1670703434&fvip=4&keepalive=yes&fexp=24001373%2C24007246&c=WEB&txp=1211222&n=wIGytpTVEhazb-6lT&sparams=expire%2Cei%2Cip%2Cid%2Caitags%2Csource%2Crequiressl%2Cgcr%2Cvprv%2Cmime%2Cns%2Cgir%2Cclen%2Cdur%2Clmt&lsparams=mh%2Cmm%2Cmn%2Cms%2Cmv%2Cmvi%2Cpcm2cms%2Cpl%2Cinitcwndbps&lsig=AG3C_xAwRQIhAPX2XBnvhqwQf98eNPHuJIXtC8lJJJMvtnvghAwLo9SFAiBsuUCj74uytqZgmn1txMEGYVPoR9DCP-RUBM_q1ZPdgg%3D%3D&sig=AOq0QJ8wRgIhALENmVqDNZRWwRWt4y7RCOuxBmxKqxgjsttyOfueEnG1AiEAhL2CrNmehnxQ3aTGtU58las-zlYjiNz7tse46d8ejG0=", "width": 1080, "ext": "webm", "vcodec": "vp9", "acodec": "none", "vbr": 531.669, "downloader_options": {"http_chunk_size": 10485760}, "container": "webm_dash", "format": "248 - 1080x1080 (1080p)", "protocol": "https", "http_headers": {"User-Agent": "Mozilla/5.0 (Windows NT 10.0; Win64; x64) AppleWebKit/537.36 (KHTML, like Gecko) Chrome/70.0.3529.3 Safari/537.36", "Accept-Charset": "ISO-8859-1,utf-8;q=0.7,*;q=0.7", "Accept": "text/html,application/xhtml+xml,application/xml;q=0.9,*/*;q=0.8", "Accept-Encoding": "gzip, deflate", "Accept-Language": "en-us,en;q=0.5"}}, {"asr": 44100, "filesize": null, "format_id": "18", "format_note": "360p", "fps": 25, "height": 360, "quality": 2, "tbr": 166.136, "url": "https://rr3---sn-0opoxu-ihv6.googlevideo.com/videoplayback?expire=1670725405&ei=veqUY5-cD430kgbHo7z4Cw&ip=189.173.225.87&id=o-AB55eTwYoeGbOIUUks_yc4l81ozMvy0OP8sXmPgo5cV8&itag=18&source=youtube&requiressl=yes&mh=Zc&mm=31%2C29&mn=sn-0opoxu-ihv6%2Csn-q4fl6nsd&ms=au%2Crdu&mv=m&mvi=3&pcm2cms=yes&pl=24&gcr=mx&initcwndbps=770000&vprv=1&mime=video%2Fmp4&ns=KZDnC8-6Jz-HAAi3K3Vsck0J&cnr=14&ratebypass=yes&dur=240.047&lmt=1637005102293962&mt=1670703434&fvip=4&fexp=24001373%2C24007246&c=WEB&txp=1218224&n=kjX-NIlW2vKEwePVv&sparams=expire%2Cei%2Cip%2Cid%2Citag%2Csource%2Crequiressl%2Cgcr%2Cvprv%2Cmime%2Cns%2Ccnr%2Cratebypass%2Cdur%2Clmt&lsparams=mh%2Cmm%2Cmn%2Cms%2Cmv%2Cmvi%2Cpcm2cms%2Cpl%2Cinitcwndbps&lsig=AG3C_xAwRQIhALd1rX2LFRqcywdkCjM8wJlOK8xlEHCDsjR-SVnQlWSQAiAeD_jAZ9n1mxz3FYTeQPMN0j6ms1ryTII855KHXSvtQQ%3D%3D&sig=AOq0QJ8wRQIhAN12PvxH9uK0hHVz9bPgZcAWU_ZgQvjDU3dtBy4yhrbgAiBNGTnTSt-qxxy1xkEm_UCklZlWHRe1DH6Yyg-dFkSy4A==", "width": 360, "ext": "mp4", "vcodec": "avc1.42001E", "acodec": "mp4a.40.2", "format": "18 - 360x360 (360p)", "protocol": "https", "http_headers": {"User-Agent": "Mozilla/5.0 (Windows NT 10.0; Win64; x64) AppleWebKit/537.36 (KHTML, like Gecko) Chrome/70.0.3529.3 Safari/537.36", "Accept-Charset": "ISO-8859-1,utf-8;q=0.7,*;q=0.7", "Accept": "text/html,application/xhtml+xml,application/xml;q=0.9,*/*;q=0.8", "Accept-Encoding": "gzip, deflate", "Accept-Language": "en-us,en;q=0.5"}}], "thumbnails": [{"height": 94, "url": "https://i.ytimg.com/vi/kzh5APxAAHA/hqdefault.jpg?sqp=-oaymwEbCKgBEF5IVfKriqkDDggBFQAAiEIYAXABwAEG&rs=AOn4CLAYk93-VFLspqriccSMSq5uGQLV9Q", "width": 168, "resolution": "168x94", "id": "0"}, {"height": 110, "url": "https://i.ytimg.com/vi/kzh5APxAAHA/hqdefault.jpg?sqp=-oaymwEbCMQBEG5IVfKriqkDDggBFQAAiEIYAXABwAEG&rs=AOn4CLAgUnAAFvalL3xEdiT2GCos-qrocA", "width": 196, "resolution": "196x110", "id": "1"}, {"height": 138, "url": "https://i.ytimg.com/vi/kzh5APxAAHA/hqdefault.jpg?sqp=-oaymwEcCPYBEIoBSFXyq4qpAw4IARUAAIhCGAFwAcABBg==&rs=AOn4CLBCGYitbIM0xWCVUJka0F4Dj2CuNA", "width": 246, "resolution": "246x138", "id": "2"}, {"height": 188, "url": "https://i.ytimg.com/vi/kzh5APxAAHA/hqdefault.jpg?sqp=-oaymwEcCNACELwBSFXyq4qpAw4IARUAAIhCGAFwAcABBg==&rs=AOn4CLDO7yZ6wZofB5Xc8h_xGPBHGTvZrg", "width": 336, "resolution": "336x188", "id": "3"}, {"height": 1080, "url": "https://i.ytimg.com/vi_webp/kzh5APxAAHA/maxresdefault.webp", "width": 1920, "resolution": "1920x1080", "id": "4"}], "description": "Provided to YouTube by NAXOS of America\n\nBehr - Polka WR: Polka W. R. \u00b7 \u0130dil Biret\n\nRachmaninov: Piano Transcriptions and Arrangements\n\n\u2117 1998 Naxos\n\nReleased on: 1998-04-15\n\nArtist: \u0130dil Biret\nComposer: Sergei Rachmaninoff\n\nAuto-generated by YouTube.", "upload_date": "20170520", "uploader": "Idil Biret - Topic", "uploader_id": "UCL4uLo_LsGKxxav8r6Qp2dQ", "uploader_url": "http://www.youtube.com/channel/UCL4uLo_LsGKxxav8r6Qp2dQ", "channel_id": "UCL4uLo_LsGKxxav8r6Qp2dQ", "channel_url": "https://www.youtube.com/channel/UCL4uLo_LsGKxxav8r6Qp2dQ", "duration": 240, "view_count": 76, "average_rating": null, "age_limit": 0, "webpage_url": "https://www.youtube.com/watch?v=kzh5APxAAHA", "categories": ["Music"], "tags": ["\u0130dil Biret", "Rachmaninov: Piano Transcriptions and Arrangements", "Behr - Polka WR: Polka W. R."], "is_live": null, "album": "Rachmaninov: Piano Transcriptions and Arrangements", "artist": "\u0130dil Biret", "track": "Behr - Polka WR: Polka W. R.", "release_date": "19980415", "release_year": 1998, "channel": "Idil Biret - Topic", "creator": "\u0130dil Biret", "alt_title": "Behr - Polka WR: Polka W. R.", "extractor": "youtube", "webpage_url_basename": "watch", "extractor_key": "Youtube", "playlist": null, "playlist_index": null, "thumbnail": "https://i.ytimg.com/vi_webp/kzh5APxAAHA/maxresdefault.webp", "display_id": "kzh5APxAAHA", "asr": 44100, "filesize": null, "format_id": "18", "format_note": "360p", "fps": 25, "height": 360, "quality": 2, "tbr": 166.136, "url": "https://rr3---sn-0opoxu-ihv6.googlevideo.com/videoplayback?expire=1670725405&ei=veqUY5-cD430kgbHo7z4Cw&ip=189.173.225.87&id=o-AB55eTwYoeGbOIUUks_yc4l81ozMvy0OP8sXmPgo5cV8&itag=18&source=youtube&requiressl=yes&mh=Zc&mm=31%2C29&mn=sn-0opoxu-ihv6%2Csn-q4fl6nsd&ms=au%2Crdu&mv=m&mvi=3&pcm2cms=yes&pl=24&gcr=mx&initcwndbps=770000&vprv=1&mime=video%2Fmp4&ns=KZDnC8-6Jz-HAAi3K3Vsck0J&cnr=14&ratebypass=yes&dur=240.047&lmt=1637005102293962&mt=1670703434&fvip=4&fexp=24001373%2C24007246&c=WEB&txp=1218224&n=kjX-NIlW2vKEwePVv&sparams=expire%2Cei%2Cip%2Cid%2Citag%2Csource%2Crequiressl%2Cgcr%2Cvprv%2Cmime%2Cns%2Ccnr%2Cratebypass%2Cdur%2Clmt&lsparams=mh%2Cmm%2Cmn%2Cms%2Cmv%2Cmvi%2Cpcm2cms%2Cpl%2Cinitcwndbps&lsig=AG3C_xAwRQIhALd1rX2LFRqcywdkCjM8wJlOK8xlEHCDsjR-SVnQlWSQAiAeD_jAZ9n1mxz3FYTeQPMN0j6ms1ryTII855KHXSvtQQ%3D%3D&sig=AOq0QJ8wRQIhAN12PvxH9uK0hHVz9bPgZcAWU_ZgQvjDU3dtBy4yhrbgAiBNGTnTSt-qxxy1xkEm_UCklZlWHRe1DH6Yyg-dFkSy4A==", "width": 360, "ext": "mp4", "vcodec": "avc1.42001E", "acodec": "mp4a.40.2", "format": "18 - 360x360 (360p)", "protocol": "https", "http_headers": {"User-Agent": "Mozilla/5.0 (Windows NT 10.0; Win64; x64) AppleWebKit/537.36 (KHTML, like Gecko) Chrome/70.0.3529.3 Safari/537.36", "Accept-Charset": "ISO-8859-1,utf-8;q=0.7,*;q=0.7", "Accept": "text/html,application/xhtml+xml,application/xml;q=0.9,*/*;q=0.8", "Accept-Encoding": "gzip, deflate", "Accept-Language": "en-us,en;q=0.5"}, "fulltitle": "Behr - Polka WR: Polka W. R.", "_filename": "Behr - Polka WR - Polka W. R.-kzh5APxAAHA.mp4"}